LICENSE
README.md
setup.py
data_explorer/__init__.py
data_explorer/date2unixtime.py
data_explorer/describe.py
data_explorer/fit_curve.py
data_explorer/plot_utils.py
data_explorer/plotter.py
data_explorer.egg-info/PKG-INFO
data_explorer.egg-info/SOURCES.txt
data_explorer.egg-info/dependency_links.txt
data_explorer.egg-info/top_level.txt