Metadata-Version: 2.1
Name: data-explorer
Version: 0.2.0
Summary: Command line utilities for data exploration
Home-page: http://github.com/perimosocordiae/data_explorer
Author: CJ Carey
Author-email: perimosocordiae@gmail.com
License: MIT
Classifier: Development Status :: 4 - Beta
Classifier: License :: OSI Approved :: MIT License
Classifier: Programming Language :: Python
Classifier: Intended Audience :: System Administrators
Classifier: Topic :: Terminals
License-File: LICENSE
